python_framework_utils/__init__.py
python_framework_utils/basic_check_util.py
python_framework_utils/common/__init__.py
python_framework_utils/common/date_time_util.py
python_framework_utils/common/file_util.py
python_framework_utils/common/json_util.py
python_framework_utils/crawler/__init__.py
python_framework_utils/crawler/headers_util.py
python_framework_utils/crawler/requests_util.py
python_framework_utils/crawler/headers/__init__.py
python_framework_utils/crawler/headers/accepts_util.py
python_framework_utils/crawler/headers/user_agents_util.py
python_framework_utils/crawler/proxy/__init__.py
python_framework_utils/crawler/proxy/dobel_proxy_util.py
python_framework_utils/crawler/proxy/script/__init__.py
python_framework_utils/crawler/proxy/script/webdriver_proxy_auth_generator_script.py
python_framework_utils/db/__init__.py
python_framework_utils/db/mysql_obj_util.py
python_framework_utils/db/mysql_util.py
python_framework_utils/video/__init__.py
python_framework_utils/video/video_util.py
python_framework_utils-0.0.2.dist-info/LICENSE
python_framework_utils-0.0.2.dist-info/METADATA
python_framework_utils-0.0.2.dist-info/WHEEL
python_framework_utils-0.0.2.dist-info/top_level.txt
python_framework_utils-0.0.2.dist-info/zip-safe
python_framework_utils-0.0.2.dist-info/RECORD
